{"name":"User can search with Google Search","id":"google-homepage-search;user-can-search-with-google-search","testSteps":[{"number":1,"description":"User can search with Google Search #1: {Search\u003dThe name of the wind, result\u003dThe Name of the Wind - Patrick Rothfuss}","duration":209,"startTime":"2020-08-21T19:28:33.923-05:00[America/Bogota]","exception":{"errorType":"java.lang.NullPointerException","stackTrace":[{"declaringClass":"testmasglobal.certification.stepdefinitions.TestMasGlobalStepDefinition","methodName":"iMOnTheHomepage","fileName":"TestMasGlobalStepDefinition.java","lineNumber":13},{"declaringClass":"✽","methodName":"I’m on the homepage","fileName":"src/test/resources/features/google/Google_homepage_search.feature","lineNumber":4}]},"result":"ERROR","precondition":false,"children":[{"number":2,"description":"Given I’m on the homepage","duration":185,"startTime":"2020-08-21T19:28:33.927-05:00[America/Bogota]","exception":{"errorType":"java.lang.NullPointerException","stackTrace":[{"declaringClass":"testmasglobal.certification.stepdefinitions.TestMasGlobalStepDefinition","methodName":"iMOnTheHomepage","fileName":"TestMasGlobalStepDefinition.java","lineNumber":13},{"declaringClass":"✽","methodName":"I’m on the homepage","fileName":"src/test/resources/features/google/Google_homepage_search.feature","lineNumber":4}]},"result":"ERROR","precondition":false},{"number":3,"description":"When I type \"The name of the wind\" into the search field","duration":2,"startTime":"2020-08-21T19:28:34.120-05:00[America/Bogota]","result":"SKIPPED","precondition":false},{"number":4,"description":"And I click the Google Search button","duration":2,"startTime":"2020-08-21T19:28:34.122-05:00[America/Bogota]","result":"SKIPPED","precondition":false},{"number":5,"description":"Then I go to the search results page","duration":2,"startTime":"2020-08-21T19:28:34.124-05:00[America/Bogota]","result":"SKIPPED","precondition":false},{"number":6,"description":"And the first result is \"The Name of the Wind - Patrick Rothfuss\"","duration":1,"startTime":"2020-08-21T19:28:34.126-05:00[America/Bogota]","result":"SKIPPED","precondition":false},{"number":7,"description":"When I click on the first result link","duration":1,"startTime":"2020-08-21T19:28:34.127-05:00[America/Bogota]","result":"PENDING","precondition":false},{"number":8,"description":"Then I go to the “Patrick Rothfuss - The Books” page","duration":1,"startTime":"2020-08-21T19:28:34.128-05:00[America/Bogota]","result":"PENDING","precondition":false}]}],"userStory":{"id":"google-homepage-search","storyName":"Google Homepage Search","path":"src/test/resources/features/google/Google_homepage_search.feature","type":"feature"},"featureTag":{"name":"Google/Google Homepage Search","type":"feature"},"title":"User can search with Google Search","tags":[{"name":"Google/Google homepage search","type":"feature"},{"name":"Google","type":"capability"}],"startTime":"2020-08-21T19:28:33.364-05:00[America/Bogota]","duration":2157,"testFailureCause":{"errorType":"java.lang.NullPointerException","stackTrace":[{"declaringClass":"testmasglobal.certification.stepdefinitions.TestMasGlobalStepDefinition","methodName":"iMOnTheHomepage","fileName":"TestMasGlobalStepDefinition.java","lineNumber":13},{"declaringClass":"✽","methodName":"I’m on the homepage","fileName":"src/test/resources/features/google/Google_homepage_search.feature","lineNumber":4}]},"testFailureClassname":"java.lang.NullPointerException","testFailureSummary":"ERROR;java.lang.NullPointerException;null;TestMasGlobalStepDefinition.java","projectKey":"","annotatedResult":"ERROR","dataTable":{"headers":["Search","result"],"rows":[{"values":["The name of the wind","The Name of the Wind - Patrick Rothfuss"],"result":"ERROR"}],"predefinedRows":true,"scenarioOutline":"Given I’m on the homepage\n\rWhen I type \"\u003cSearch\u003e\" into the search field\n\rAnd I click the Google Search button\n\rThen I go to the search results page\n\rAnd the first result is \"\u003cresult\u003e\"\n\rWhen I click on the first result link\n\rThen I go to the “Patrick Rothfuss - The Books” page\n\r","dataSetDescriptors":[{"startRow":0,"rowCount":0,"name":""}]},"manual":false,"testSource":"Cucumber","result":"ERROR"}